RollingHorizonEA/__init__.py
RollingHorizonEA/environment.py
RollingHorizonEA/rhea.py
RollingHorizonEA-0.1.2.dist-info/LICENSE
RollingHorizonEA-0.1.2.dist-info/METADATA
RollingHorizonEA-0.1.2.dist-info/WHEEL
RollingHorizonEA-0.1.2.dist-info/top_level.txt
RollingHorizonEA-0.1.2.dist-info/RECORD
