Metadata-Version: 2.1
Name: RollingHorizonEA
Version: 0.1.2
Summary: Rolling Horizon Evolutionary Algorithm
Home-page: https://github.com/bam4d/RollingHorizonEvolutionaryAlgorithm
Author: Chris Bamford
Author-email: chrisbam4d@gmail.com
License: UNKNOWN
Platform: UNKNOWN
Classifier: Programming Language :: Python :: 3
Classifier: License :: OSI Approved :: GNU General Public License v3 (GPLv3)
Classifier: Operating System :: OS Independent
